{"id":"g19cobmk3lnn50wk095xqeg","title":"SemVer Breaking Changes","desc":"","updated":1680034919517,"created":1679957276085,"custom":{},"fname":"tech.philosophy.versioning.semver.breaking","type":"note","vault":{"fsPath":".","selfContained":true,"name":"Dendron"},"contentHash":"da93ce2e3d2f76ff2bb150ae62097950","links":[{"type":"wiki","from":{"fname":"tech.philosophy.versioning.semver.breaking","id":"g19cobmk3lnn50wk095xqeg","vaultName":"Dendron"},"value":"tech.philosophy.laws.hyrum","position":{"start":{"line":3,"column":49,"offset":78},"end":{"line":3,"column":79,"offset":108},"indent":[]},"xvault":false,"sameFile":false,"to":{"fname":"tech.philosophy.laws.hyrum"}}],"anchors":{"what-is-a-breaking-change":{"type":"header","text":"What is a Breaking Change?","value":"what-is-a-breaking-change","line":8,"column":0,"depth":1},"behavioral-change":{"type":"header","text":"Behavioral Change","value":"behavioral-change","line":13,"column":0,"depth":2},"performance-changes":{"type":"header","text":"Performance Changes","value":"performance-changes","line":36,"column":0,"depth":2},"automated-testing":{"type":"header","text":"Automated Testing","value":"automated-testing","line":41,"column":0,"depth":2},"theyre-all-potentially-breaking":{"type":"header","text":"They're All Potentially Breaking!","value":"theyre-all-potentially-breaking","line":46,"column":0,"depth":2}},"children":[],"parent":"semver","data":{}}
